Xilinx/fsm/fsm.v
module finite_state(clk, reset, c, r, view_price, view_quantity, view_price_q, entered_amount);
	input clk, reset;
	input  [3:0]c;
	input  [3:0]r;
	output reg [7:0]view_price;
	output reg [7:0]view_quantity; 
	output reg [7:0]view_price_q;
	output reg [7:0]entered_amount;


	reg [2:0]state,nstate;
	parameter s0 = 3'b000;
	parameter s1 = 3'b001;
	parameter s2 = 3'b010;
	parameter s3 = 3'b011;
	parameter s4 = 3'b100;
	parameter s5 = 3'b101;
	parameter s6 = 3'b110; 
	reg product_select;
	reg [7:0]entered_amount_2=0;
	reg [7:0]entered_amount_5=0;
	reg [7:0]entered_amount_10=0;
	reg product_taken;
	reg [7:0]count=8'b00000101;
				
	always @(posedge clk or negedge reset)
		begin
			if(!reset)
			state <= s0;
			else 
			state <= nstate;
			end

	always @(posedge clk or negedge reset)
		begin
			case (state)
			
			s0: //reset state
			begin
			if(c[3] == 0 && r[3] == 0) //start button
			nstate = s1;
			else 
			nstate = s0;
			end
			
			s1: //select product state
			begin 
			
			if (c[0] == 0 && r[0] == 0)
			begin
			product_select = 1; //product_chips
			view_price = 8'h0F; //product chips $15
			end
			
			else if(c[0] == 0 && r[1] ==0)
			begin
			product_select = 1; // product_coke
			view_price = 8'h0C; // product_coke $12
			end
			
			else if(c[0] == 0 && r[2] ==0)
			begin
			product_select = 1; //product_cookie
			view_price = 8'h0A; //product_cookie $10 
			end
			
			else if (c[0] == 0 && r[3] == 0)
			begin
			product_select = 1; //product_icecream
			view_price = 8'h08; //product_icecream $5
			end

			else if (c[1] ==0 && r[0] ==0)
			begin
			product_select =1; //product_coffee
			view_price = 8'h02; //product_coffee $2
			end

			else
			product_select = 0;
			if(product_select == 1)
			nstate = s2;
			else
			nstate = s0;
			end

			s2: // view price
			begin
			if (view_price != 8'h00)
			nstate = s3;
			else 
			nstate = s1;
			end
			
			s3: // select qunatity state
			begin 
			//if(c[1] == 0 && r[1] == 0)
			view_quantity = count;

			if (c[1] == 0 && r[2] == 0)
			nstate = s4;
			
//			else if (!reset)
//			nstate = s1;		
		end

		s4: // confirm selection
			begin
			view_price_q = view_quantity*view_price;
			if(c[1] == 0 && r[3] == 0) //confirm price
			nstate = s5;
			
			else if(!reset)
			nstate = s1;
			end
			
			s5: // Enter amount
			begin 
			if (c[2] == 0 && r[0] ==0) 
			entered_amount_2 = count*2;
		else	if (c[2] == 0 && r[1] ==0)
			entered_amount_5 = count*5;
		else	if (c[2] == 0 && r[2] ==0)
			entered_amount_10 = count*10 ;

			entered_amount = entered_amount_2 + entered_amount_5 + entered_amount_10;

			if (entered_amount == view_price_q)
			nstate = s6;
			else if (!reset)
			nstate = s1;
			end
			
			s6: 
			begin
			if (c[2] == 0 && r[3] == 0)
			product_taken = 1;
			nstate = s0; 
			end
			
			default : state = s0; 
		
			endcase
			end
			
			initial begin
			$monitor("c=%b, r=%b, nstate=%b, state =%b,view_price=%d, view_price_q=%d, view_quantity=%d, entered_amount=%d, clk=%b, reset=%b, count=%d",c,r,nstate,state,view_price,view_price_q,view_quantity,entered_amount,clk,reset,count);
			$dumpvars();
			$dumpfile("finitestatemachine.vcd");
			end
			endmodule

Xilinx/fsm/fsm_testbench.v

module finitestatemachine_tb();

	// Inputs
	reg clk;
	reg reset;
	reg [3:0] c;
	reg [3:0] r;

	// Outputs
	wire [7:0]view_price;
	wire [7:0]view_quantity;
	wire [7:0]view_price_q;
	wire [7:0]entered_amount;

	// Instantiate the Unit Under Test (UUT)
	finite_state uut(
		.clk(clk), 
		.reset(reset), 
		.c(c), 
		.r(r), 
		.view_price(view_price), 
		.view_quantity(view_quantity), 
		.view_price_q(view_price_q), 
		.entered_amount(entered_amount)
	);

	always #5 clk = ~clk;
	
	initial begin
		// Initialize Inputs
		clk = 0;
		reset = 0;

		// Wait 100 ns for global reset to finish
		#100;
		
		reset = 1;
		c = 4'b1111;
		r = 4'b1111;
		
		#10;
		//start button
		c = 4'b0111;
		r = 4'b0111;

		#20;
		//product_select = chips
		c = 4'b1110;
		r = 4'b1110;

			
#20;
		//select quantity
		c = 4'b1101;
		r = 4'b1101;
		
	

		#20
		//confirm quantity selection
		c = 4'b1101;
		r = 4'b1011;

		#20
		//confirm price
		c = 4'b1101;
		r = 4'b0111;
		#20
		c = 4'b1011;
		r = 4'b1101;
		#20		
		c = 4'b1011;
		r = 4'b1011;
		#20		
		c = 4'b1011;
		r = 4'b0111;

	#50;
		$finish;
		
		
		
        
		// Add stimulus here

	end
      
endmodule

Xilinx/fsm/dump.vcd
$date
   Mon Dec 02 18:44:51 2019
$end
$version
  P.20131013
$end
$timescale
  1ps
$end
$scope module finitestatemachine_tb $end
$scope module uut $end
$var wire 1 ! clk $end
$var wire 1 " reset $end
$var wire 1 # c [3] $end
$var wire 1 $ c [2] $end
$var wire 1 % c [1] $end
$var wire 1 & c [0] $end
$var wire 1 ' r [3] $end
$var wire 1 ( r [2] $end
$var wire 1 ) r [1] $end
$var wire 1 * r [0] $end
$var reg 8 + view_price [7:0] $end
$var reg 8 , view_quantity [7:0] $end
$var reg 8 - view_price_q [7:0] $end
$var reg 8 . entered_amount [7:0] $end
$var reg 3 / state [2:0] $end
$var reg 3 0 nstate [2:0] $end
$var reg 1 1 product_select $end
$var reg 8 2 entered_amount_2 [7:0] $end
$var reg 8 3 entered_amount_5 [7:0] $end
$var reg 8 4 entered_amount_10 [7:0] $end
$var reg 1 5 product_taken $end
$var reg 8 6 count [7:0] $end
$upscope $end
$upscope $end
$enddefinitions $end
#0
$dumpvars
bx +
bx ,
bx -
bx .
b0 /
bx 0
x1
b0 2
b0 3
b0 4
x5
b101 6
0"
x$
x&
x*
x%
x(
0!
x'
x#
x)
$end
#5000
b0 0
1!
#10000
0!
#15000
1!
#20000
0!
#25000
1!
#30000
0!
#35000
1!
#40000
0!
#45000
1!
#50000
0!
#55000
1!
#60000
0!
#65000
1!
#70000
0!
#75000
1!
#80000
0!
#85000
1!
#90000
0!
#95000
1!
#100000
1"
1$
1&
1*
1%
1(
0!
1'
1#
1)
#105000
1!
#110000
0!
0'
0#
#115000
b1 0
1!
#120000
0!
#125000
b1 /
1!
#130000
0&
0*
0!
1'
1#
#135000
b1111 +
b10 0
11
1!
#140000
0!
#145000
b10 /
1!
#150000
1&
1*
0%
0!
0)
#155000
b11 0
1!
#160000
0!
#165000
b11 /
1!
#170000
0(
0!
1)
#175000
b101 ,
b100 0
1!
#180000
0!
#185000
b100 /
1!
#190000
1(
0!
0'
#195000
b1001011 -
b101 0
1!
#200000
0!
#205000
b101 /
1!
#210000
0$
1%
0!
1'
0)
#215000
b11001 .
b11001 3
1!
#220000
0!
#225000
1!
#230000
0(
0!
1)
#235000
b1001011 .
b110 0
b110010 4
1!
#240000
0!
#245000
b110 /
1!
#250000
1(
0!
0'
#255000
b0 0
15
1!
#260000
0!
#265000
b0 /
1!
